{
  "schedules": [
    {
      "id": "1747358717191",
      "name": "Diego Coelho",
      "when": "2025-05-17T21:00:00.000Z"
    },
    {
      "id": 1747361494543,
      "name": "Marcelo",
      "when": "2025-05-17T20:00:00.000Z"
    },
    {
      "id": 1747362154404,
      "name": "marcos",
      "when": "2025-05-17T18:00:00.000Z"
    },
    {
      "id": 1747362347237,
      "name": "Josué",
      "when": "2025-05-17T23:00:00.000Z"
    },
    {
      "id": 1747362355740,
      "name": "Maria",
      "when": "2025-05-17T12:00:00.000Z"
    }
  ]
}